mc_authn/__init__.py
mc_authn-1.0.5.dist-info/LICENSE
mc_authn-1.0.5.dist-info/METADATA
mc_authn-1.0.5.dist-info/WHEEL
mc_authn-1.0.5.dist-info/entry_points.txt
mc_authn-1.0.5.dist-info/top_level.txt
mc_authn-1.0.5.dist-info/RECORD
