Metadata-Version: 2.1
Name: mc-authn
Version: 1.0.5
Summary: Python Authenticator for Minecraft with Microsoft
Home-page: https://github.com/hykilpikonna/mc-auth
Author: Azalea Gui
Author-email: me@hydev.org
License: MIT
Platform: UNKNOWN
Classifier: License :: OSI Approved :: MIT License
Classifier: Programming Language :: Python :: 3
Classifier: Programming Language :: Python :: 3.7
Classifier: Programming Language :: Python :: 3.8
Classifier: Programming Language :: Python :: 3.9
Classifier: Programming Language :: Python :: 3.10
License-File: LICENSE
Requires-Dist: setuptools
Requires-Dist: typing-extensions
Requires-Dist: fastapi (~=0.81.0)
Requires-Dist: uvicorn (~=0.18.3)
Requires-Dist: ruamel.yaml
Requires-Dist: hypy-utils (>=1.0.13)
